<annotation>
  <folder>backup</folder>
  <filename>chuyentiep_1</filename>
  <path>E:\Data\Pycharm Project\PT_ObjectDetection\Label\backup\chuyentiep_1.jpg</path>
  <source>
    <database>Unknown</database>
  </source>
  <size>
    <width>1150</width>
    <height>750</height>
    <depth>3</depth>
  </size>
  <segmented>0</segmented>
  <object>
    <name>chuyentiep</name>
    <pose>Unspecified</pose>
    <truncated>0</truncated>
    <difficult>0</difficult>
    <bndbox>
      <xmin>356</xmin>
      <ymin>554</ymin>
      <xmax>561</xmax>
      <ymax>650</ymax>
    </bndbox>
  </object>
  <object>
    <name>trieuca</name>
    <pose>Unspecified</pose>
    <truncated>0</truncated>
    <difficult>0</difficult>
    <bndbox>
      <xmin>1038</xmin>
      <ymin>2</ymin>
      <xmax>1107</xmax>
      <ymax>19</ymax>
    </bndbox>
  </object>
</annotation>
